pythsr/__init__.py
pythsr-0.6.dist-info/LICENSE
pythsr-0.6.dist-info/METADATA
pythsr-0.6.dist-info/WHEEL
pythsr-0.6.dist-info/top_level.txt
pythsr-0.6.dist-info/RECORD
