Metadata-Version: 2.1
Name: pythsr
Version: 0.6
Summary: A collection of python utils for personal use
Home-page: http://github.com/thsr/pythsr
Author: thsr
Author-email: 437808@gmail.com
License: MIT
Platform: UNKNOWN
Classifier: Programming Language :: Python :: 3
Classifier: License :: OSI Approved :: MIT License
Classifier: Operating System :: OS Independent
